{
  "manifestVersion": "3.2",
  "proxies": [
    {
      "address": "0x5725D6754b12F37b7c6455d34704D1727A78C7ca",
      "txHash": "0x2a2479aa6c34aa751b035319652ecf0d6d852a0d5f821fd69688311c5322dc82",
      "kind": "transparent"
    },
    {
      "address": "0x8334E98bBB92e4c729305f265E25156E6412f46F",
      "txHash": "0x94e4e2887bba8676b43915a7ea17ba47a3359d46d0c664a97a67ad337dc9dc21",
      "kind": "transparent"
    },
    {
      "address": "0x3d3e057714a8c29d54daFa7Da7Ae166449B3115A",
      "txHash": "0x634609e0351fb9227f4f36261b0cc1785f75566baa7da10669e8ef6f92bb6a21",
      "kind": "transparent"
    },
    {
      "address": "0x9a4255cAE62b6d0BC4dFe0E29705aa3AB0985F6A",
      "txHash": "0x3d54a1ecf424e982c245034ab5847c33371c077fe09d37d344a21ec927acbb25",
      "kind": "transparent"
    },
    {
      "address": "0x62f447De4e7695EaeB7A4d5902707528c0a59c30",
      "txHash": "0x3c105cd9c8b67947a0f08496362d1da0b701f96e88ac0b573c02789bf3984802",
      "kind": "transparent"
    },
    {
      "address": "0x7189ce02622c20EdDb6579D32B558F537293C0Cd",
      "txHash": "0x1ed0e25204f7a4aef733f1a101f235f6b38eb143d2133d1c39e4bbb131302b6a",
      "kind": "transparent"
    },
    {
      "address": "0x5899de41cD75d8919b95EA639e7Bbe674fE97261",
      "txHash": "0x636816a2be78dcb686a909e3602f5eb285d2c84e18f53675122cc478947fa73d",
      "kind": "transparent"
    },
    {
      "address": "0xfeCE70d0e9bb0c911890f036321a8a463a77Ab03",
      "txHash": "0xaef57d4211df0f6c3ecc822b0ea3d6d17a4b57831d5caa283aa9faf966a90e90",
      "kind": "transparent"
    },
    {
      "address": "0x5Bc82216107ea117d700B9AC1D2790e9388B77C4",
      "txHash": "0x115631975ccfad8e3bb42420998c44cf9648f7aa12be4981707cc952e5a57962",
      "kind": "transparent"
    },
    {
      "address": "0xB4Cd004f01AC5A428f169F956192415722A9fb3C",
      "txHash": "0x570a289f7b76685b8509113d165c65c9ff8cb2d01c28845bc5a27ee53952ec1a",
      "kind": "transparent"
    },
    {
      "address": "0x9DcBE00Afb4526A5ea180b399F1Ac57E30478f8E",
      "txHash": "0xf98a2165cad86918d997c9de4fed3ef99db1fdce4b9fcd433c304b176de1c996",
      "kind": "transparent"
    }
  ],
  "impls": {
    "4fd276e1deeab2a15591f09b8c4fa29881d28ec359233f7dc5b4f30c712e1f18": {
      "address": "0x4755b463a5eB21A7A3ABc5A80CE0E86aAf4D1A1A",
      "txHash": "0x4955bd75078e6aa670c4f922d8094b89394f95cdaef640e739dcc0b037c4df06",
      "layout": {
        "solcVersion": "0.8.24",
        "storage": [
          {
            "label": "_initialized",
            "offset": 0,
            "slot": "0",
            "type": "t_uint8",
            "contract": "Initializable",
            "src": "@openzeppelin\\contracts-upgradeable\\proxy\\utils\\Initializable.sol:63",
            "retypedFrom": "bool"
          },
          {
            "label": "_initializing",
            "offset": 1,
            "slot": "0",
            "type": "t_bool",
            "contract": "Initializable",
            "src": "@openzeppelin\\contracts-upgradeable\\proxy\\utils\\Initializable.sol:68"
          },
          {
            "label": "__gap",
            "offset": 0,
            "slot": "1",
            "type": "t_array(t_uint256)50_storage",
            "contract": "ContextUpgradeable",
            "src": "@openzeppelin\\contracts-upgradeable\\utils\\ContextUpgradeable.sol:40"
          },
          {
            "label": "_owner",
            "offset": 0,
            "slot": "51",
            "type": "t_address",
            "contract": "OwnableUpgradeable",
            "src": "@openzeppelin\\contracts-upgradeable\\access\\OwnableUpgradeable.sol:22"
          },
          {
            "label": "__gap",
            "offset": 0,
            "slot": "52",
            "type": "t_array(t_uint256)49_storage",
            "contract": "OwnableUpgradeable",
            "src": "@openzeppelin\\contracts-upgradeable\\access\\OwnableUpgradeable.sol:94"
          },
          {
            "label": "campaigns",
            "offset": 0,
            "slot": "101",
            "type": "t_array(t_struct(FundingCampaign)1432_storage)dyn_storage",
            "contract": "Funding",
            "src": "contracts\\Funding.sol:23"
          }
        ],
        "types": {
          "t_address": {
            "label": "address",
            "numberOfBytes": "20"
          },
          "t_array(t_address)dyn_storage": {
            "label": "address[]",
            "numberOfBytes": "32"
          },
          "t_array(t_struct(FundingCampaign)1432_storage)dyn_storage": {
            "label": "struct Funding.FundingCampaign[]",
            "numberOfBytes": "32"
          },
          "t_array(t_uint256)49_storage": {
            "label": "uint256[49]",
            "numberOfBytes": "1568"
          },
          "t_array(t_uint256)50_storage": {
            "label": "uint256[50]",
            "numberOfBytes": "1600"
          },
          "t_array(t_uint256)dyn_storage": {
            "label": "uint256[]",
            "numberOfBytes": "32"
          },
          "t_bool": {
            "label": "bool",
            "numberOfBytes": "1"
          },
          "t_string_storage": {
            "label": "string",
            "numberOfBytes": "32"
          },
          "t_struct(FundingCampaign)1432_storage": {
            "label": "struct Funding.FundingCampaign",
            "members": [
              {
                "label": "title",
                "type": "t_string_storage",
                "offset": 0,
                "slot": "0"
              },
              {
                "label": "description",
                "type": "t_string_storage",
                "offset": 0,
                "slot": "1"
              },
              {
                "label": "owner",
                "type": "t_address",
                "offset": 0,
                "slot": "2"
              },
              {
                "label": "goal",
                "type": "t_uint256",
                "offset": 0,
                "slot": "3"
              },
              {
                "label": "raised",
                "type": "t_uint256",
                "offset": 0,
                "slot": "4"
              },
              {
                "label": "active",
                "type": "t_bool",
                "offset": 0,
                "slot": "5"
              },
              {
                "label": "contributors",
                "type": "t_array(t_address)dyn_storage",
                "offset": 0,
                "slot": "6"
              },
              {
                "label": "contributions",
                "type": "t_array(t_uint256)dyn_storage",
                "offset": 0,
                "slot": "7"
              },
              {
                "label": "ipfsUuid",
                "type": "t_string_storage",
                "offset": 0,
                "slot": "8"
              }
            ],
            "numberOfBytes": "288"
          },
          "t_uint256": {
            "label": "uint256",
            "numberOfBytes": "32"
          },
          "t_uint8": {
            "label": "uint8",
            "numberOfBytes": "1"
          }
        },
        "namespaces": {}
      }
    },
    "4e6457b6090c18d8b52bfbf6a7d405d312544004bf554b4a9714fb630b198779": {
      "address": "0x101A4cACB296F11eB14Ee81Ca28800D93a8beD5E",
      "txHash": "0x7b5184803134c6c9380b2b68ca8e7bb11aeb2f0c7c87eae17b7750b8fe646db8",
      "layout": {
        "solcVersion": "0.8.24",
        "storage": [
          {
            "label": "_initialized",
            "offset": 0,
            "slot": "0",
            "type": "t_uint8",
            "contract": "Initializable",
            "src": "@openzeppelin\\contracts-upgradeable\\proxy\\utils\\Initializable.sol:63",
            "retypedFrom": "bool"
          },
          {
            "label": "_initializing",
            "offset": 1,
            "slot": "0",
            "type": "t_bool",
            "contract": "Initializable",
            "src": "@openzeppelin\\contracts-upgradeable\\proxy\\utils\\Initializable.sol:68"
          },
          {
            "label": "__gap",
            "offset": 0,
            "slot": "1",
            "type": "t_array(t_uint256)50_storage",
            "contract": "ContextUpgradeable",
            "src": "@openzeppelin\\contracts-upgradeable\\utils\\ContextUpgradeable.sol:40"
          },
          {
            "label": "_owner",
            "offset": 0,
            "slot": "51",
            "type": "t_address",
            "contract": "OwnableUpgradeable",
            "src": "@openzeppelin\\contracts-upgradeable\\access\\OwnableUpgradeable.sol:22"
          },
          {
            "label": "__gap",
            "offset": 0,
            "slot": "52",
            "type": "t_array(t_uint256)49_storage",
            "contract": "OwnableUpgradeable",
            "src": "@openzeppelin\\contracts-upgradeable\\access\\OwnableUpgradeable.sol:94"
          },
          {
            "label": "itf",
            "offset": 0,
            "slot": "101",
            "type": "t_contract(I)692",
            "contract": "Funding",
            "src": "contracts\\Funding.sol:13"
          },
          {
            "label": "campaigns",
            "offset": 0,
            "slot": "102",
            "type": "t_array(t_struct(FundingCampaign)720_storage)dyn_storage",
            "contract": "Funding",
            "src": "contracts\\Funding.sol:27"
          }
        ],
        "types": {
          "t_address": {
            "label": "address",
            "numberOfBytes": "20"
          },
          "t_array(t_address)dyn_storage": {
            "label": "address[]",
            "numberOfBytes": "32"
          },
          "t_array(t_struct(FundingCampaign)720_storage)dyn_storage": {
            "label": "struct Funding.FundingCampaign[]",
            "numberOfBytes": "32"
          },
          "t_array(t_uint256)49_storage": {
            "label": "uint256[49]",
            "numberOfBytes": "1568"
          },
          "t_array(t_uint256)50_storage": {
            "label": "uint256[50]",
            "numberOfBytes": "1600"
          },
          "t_array(t_uint256)dyn_storage": {
            "label": "uint256[]",
            "numberOfBytes": "32"
          },
          "t_bool": {
            "label": "bool",
            "numberOfBytes": "1"
          },
          "t_contract(I)692": {
            "label": "contract I",
            "numberOfBytes": "20"
          },
          "t_string_storage": {
            "label": "string",
            "numberOfBytes": "32"
          },
          "t_struct(FundingCampaign)720_storage": {
            "label": "struct Funding.FundingCampaign",
            "members": [
              {
                "label": "title",
                "type": "t_string_storage",
                "offset": 0,
                "slot": "0"
              },
              {
                "label": "description",
                "type": "t_string_storage",
                "offset": 0,
                "slot": "1"
              },
              {
                "label": "owner",
                "type": "t_address",
                "offset": 0,
                "slot": "2"
              },
              {
                "label": "goal",
                "type": "t_uint256",
                "offset": 0,
                "slot": "3"
              },
              {
                "label": "raised",
                "type": "t_uint256",
                "offset": 0,
                "slot": "4"
              },
              {
                "label": "active",
                "type": "t_bool",
                "offset": 0,
                "slot": "5"
              },
              {
                "label": "contributors",
                "type": "t_array(t_address)dyn_storage",
                "offset": 0,
                "slot": "6"
              },
              {
                "label": "contributions",
                "type": "t_array(t_uint256)dyn_storage",
                "offset": 0,
                "slot": "7"
              },
              {
                "label": "ipfsUuid",
                "type": "t_string_storage",
                "offset": 0,
                "slot": "8"
              }
            ],
            "numberOfBytes": "288"
          },
          "t_uint256": {
            "label": "uint256",
            "numberOfBytes": "32"
          },
          "t_uint8": {
            "label": "uint8",
            "numberOfBytes": "1"
          }
        },
        "namespaces": {}
      }
    },
    "cf05b6d685568e3c6f7e26b9f16f82e4807e029a322e839c5b42bf2388ec0c12": {
      "address": "0xa79F809caa0b5f0803A3DC9Cee7B26d0bD3d096C",
      "txHash": "0x1725b5be68f5006991d84c6a2907a87dcab25f3106b6a5697ce569b1f0c9e980",
      "layout": {
        "solcVersion": "0.8.24",
        "storage": [
          {
            "label": "_initialized",
            "offset": 0,
            "slot": "0",
            "type": "t_uint8",
            "contract": "Initializable",
            "src": "@openzeppelin\\contracts-upgradeable\\proxy\\utils\\Initializable.sol:63",
            "retypedFrom": "bool"
          },
          {
            "label": "_initializing",
            "offset": 1,
            "slot": "0",
            "type": "t_bool",
            "contract": "Initializable",
            "src": "@openzeppelin\\contracts-upgradeable\\proxy\\utils\\Initializable.sol:68"
          },
          {
            "label": "__gap",
            "offset": 0,
            "slot": "1",
            "type": "t_array(t_uint256)50_storage",
            "contract": "ContextUpgradeable",
            "src": "@openzeppelin\\contracts-upgradeable\\utils\\ContextUpgradeable.sol:40"
          },
          {
            "label": "_owner",
            "offset": 0,
            "slot": "51",
            "type": "t_address",
            "contract": "OwnableUpgradeable",
            "src": "@openzeppelin\\contracts-upgradeable\\access\\OwnableUpgradeable.sol:22"
          },
          {
            "label": "__gap",
            "offset": 0,
            "slot": "52",
            "type": "t_array(t_uint256)49_storage",
            "contract": "OwnableUpgradeable",
            "src": "@openzeppelin\\contracts-upgradeable\\access\\OwnableUpgradeable.sol:94"
          },
          {
            "label": "itf",
            "offset": 0,
            "slot": "101",
            "type": "t_contract(I)692",
            "contract": "Funding",
            "src": "contracts\\Funding.sol:13"
          },
          {
            "label": "campaigns",
            "offset": 0,
            "slot": "102",
            "type": "t_array(t_struct(FundingCampaign)720_storage)dyn_storage",
            "contract": "Funding",
            "src": "contracts\\Funding.sol:27"
          }
        ],
        "types": {
          "t_address": {
            "label": "address",
            "numberOfBytes": "20"
          },
          "t_array(t_address)dyn_storage": {
            "label": "address[]",
            "numberOfBytes": "32"
          },
          "t_array(t_struct(FundingCampaign)720_storage)dyn_storage": {
            "label": "struct Funding.FundingCampaign[]",
            "numberOfBytes": "32"
          },
          "t_array(t_uint256)49_storage": {
            "label": "uint256[49]",
            "numberOfBytes": "1568"
          },
          "t_array(t_uint256)50_storage": {
            "label": "uint256[50]",
            "numberOfBytes": "1600"
          },
          "t_array(t_uint256)dyn_storage": {
            "label": "uint256[]",
            "numberOfBytes": "32"
          },
          "t_bool": {
            "label": "bool",
            "numberOfBytes": "1"
          },
          "t_contract(I)692": {
            "label": "contract I",
            "numberOfBytes": "20"
          },
          "t_string_storage": {
            "label": "string",
            "numberOfBytes": "32"
          },
          "t_struct(FundingCampaign)720_storage": {
            "label": "struct Funding.FundingCampaign",
            "members": [
              {
                "label": "title",
                "type": "t_string_storage",
                "offset": 0,
                "slot": "0"
              },
              {
                "label": "description",
                "type": "t_string_storage",
                "offset": 0,
                "slot": "1"
              },
              {
                "label": "owner",
                "type": "t_address",
                "offset": 0,
                "slot": "2"
              },
              {
                "label": "goal",
                "type": "t_uint256",
                "offset": 0,
                "slot": "3"
              },
              {
                "label": "raised",
                "type": "t_uint256",
                "offset": 0,
                "slot": "4"
              },
              {
                "label": "active",
                "type": "t_bool",
                "offset": 0,
                "slot": "5"
              },
              {
                "label": "contributors",
                "type": "t_array(t_address)dyn_storage",
                "offset": 0,
                "slot": "6"
              },
              {
                "label": "contributions",
                "type": "t_array(t_uint256)dyn_storage",
                "offset": 0,
                "slot": "7"
              },
              {
                "label": "ipfsUuid",
                "type": "t_string_storage",
                "offset": 0,
                "slot": "8"
              }
            ],
            "numberOfBytes": "288"
          },
          "t_uint256": {
            "label": "uint256",
            "numberOfBytes": "32"
          },
          "t_uint8": {
            "label": "uint8",
            "numberOfBytes": "1"
          }
        },
        "namespaces": {}
      }
    },
    "b13683d5678537a8e53c3f3878e15f94092c521b211340a876f2a66ac4f9c5b6": {
      "address": "0x5d220720e6073b865378860f2A350A9db6D84E7D",
      "txHash": "0x84b4c47e5b4fd1f697e27dcee0e8fa4c2dcf37f30497bfbab671e4dd7774b7c3",
      "layout": {
        "solcVersion": "0.8.24",
        "storage": [
          {
            "label": "_initialized",
            "offset": 0,
            "slot": "0",
            "type": "t_uint8",
            "contract": "Initializable",
            "src": "@openzeppelin\\contracts-upgradeable\\proxy\\utils\\Initializable.sol:63",
            "retypedFrom": "bool"
          },
          {
            "label": "_initializing",
            "offset": 1,
            "slot": "0",
            "type": "t_bool",
            "contract": "Initializable",
            "src": "@openzeppelin\\contracts-upgradeable\\proxy\\utils\\Initializable.sol:68"
          },
          {
            "label": "__gap",
            "offset": 0,
            "slot": "1",
            "type": "t_array(t_uint256)50_storage",
            "contract": "ContextUpgradeable",
            "src": "@openzeppelin\\contracts-upgradeable\\utils\\ContextUpgradeable.sol:40"
          },
          {
            "label": "_owner",
            "offset": 0,
            "slot": "51",
            "type": "t_address",
            "contract": "OwnableUpgradeable",
            "src": "@openzeppelin\\contracts-upgradeable\\access\\OwnableUpgradeable.sol:22"
          },
          {
            "label": "__gap",
            "offset": 0,
            "slot": "52",
            "type": "t_array(t_uint256)49_storage",
            "contract": "OwnableUpgradeable",
            "src": "@openzeppelin\\contracts-upgradeable\\access\\OwnableUpgradeable.sol:94"
          },
          {
            "label": "itf",
            "offset": 0,
            "slot": "101",
            "type": "t_contract(I)692",
            "contract": "Funding",
            "src": "contracts\\Funding.sol:13"
          },
          {
            "label": "campaigns",
            "offset": 0,
            "slot": "102",
            "type": "t_array(t_struct(FundingCampaign)720_storage)dyn_storage",
            "contract": "Funding",
            "src": "contracts\\Funding.sol:27"
          }
        ],
        "types": {
          "t_address": {
            "label": "address",
            "numberOfBytes": "20"
          },
          "t_array(t_address)dyn_storage": {
            "label": "address[]",
            "numberOfBytes": "32"
          },
          "t_array(t_struct(FundingCampaign)720_storage)dyn_storage": {
            "label": "struct Funding.FundingCampaign[]",
            "numberOfBytes": "32"
          },
          "t_array(t_uint256)49_storage": {
            "label": "uint256[49]",
            "numberOfBytes": "1568"
          },
          "t_array(t_uint256)50_storage": {
            "label": "uint256[50]",
            "numberOfBytes": "1600"
          },
          "t_array(t_uint256)dyn_storage": {
            "label": "uint256[]",
            "numberOfBytes": "32"
          },
          "t_bool": {
            "label": "bool",
            "numberOfBytes": "1"
          },
          "t_contract(I)692": {
            "label": "contract I",
            "numberOfBytes": "20"
          },
          "t_string_storage": {
            "label": "string",
            "numberOfBytes": "32"
          },
          "t_struct(FundingCampaign)720_storage": {
            "label": "struct Funding.FundingCampaign",
            "members": [
              {
                "label": "title",
                "type": "t_string_storage",
                "offset": 0,
                "slot": "0"
              },
              {
                "label": "description",
                "type": "t_string_storage",
                "offset": 0,
                "slot": "1"
              },
              {
                "label": "owner",
                "type": "t_address",
                "offset": 0,
                "slot": "2"
              },
              {
                "label": "goal",
                "type": "t_uint256",
                "offset": 0,
                "slot": "3"
              },
              {
                "label": "raised",
                "type": "t_uint256",
                "offset": 0,
                "slot": "4"
              },
              {
                "label": "active",
                "type": "t_bool",
                "offset": 0,
                "slot": "5"
              },
              {
                "label": "contributors",
                "type": "t_array(t_address)dyn_storage",
                "offset": 0,
                "slot": "6"
              },
              {
                "label": "contributions",
                "type": "t_array(t_uint256)dyn_storage",
                "offset": 0,
                "slot": "7"
              },
              {
                "label": "ipfsUuid",
                "type": "t_string_storage",
                "offset": 0,
                "slot": "8"
              }
            ],
            "numberOfBytes": "288"
          },
          "t_uint256": {
            "label": "uint256",
            "numberOfBytes": "32"
          },
          "t_uint8": {
            "label": "uint8",
            "numberOfBytes": "1"
          }
        },
        "namespaces": {}
      }
    }
  }
}
